{"map":[{"class":"handguard","default":"m4-std-handguard","modelName":"handguard"},{"class":"gasblock","default":"m4fs-gasblock","modelName":"gasblock"},{"class":"barrelEnd","modelName":"barrelEnd","mountType":"m4_barrel"}],"attributes":{"camo":[{"name":"Default","fields":[{"adornee":"{this}","properties":{"TextureID":"rbxassetid://6477196481"}}]},{"name":"Tan","fields":[{"adornee":"{this}","properties":{"TextureID":"rbxassetid://8080283621"}}]}]},"stats":{"verticalRecoil":-2,"weight":0.3,"bullet_velocity":-200,"horizontalRecoil":-2,"ergonomics":1},"previewFov":4,"name":"260mm 5.56","preview_rotation":1,"attachName":"Barrel"}